jupyterlab_mutableai_optin/__init__.py
jupyterlab_mutableai_optin/_version.py
jupyterlab_mutableai_optin/labextension/build_log.json
jupyterlab_mutableai_optin/labextension/package.json
jupyterlab_mutableai_optin/labextension/static/551302024f9f9dcad3fd02d7bbfcd628cf81d75a81202edb87758d23aaa619ab.png
jupyterlab_mutableai_optin/labextension/static/lib_index_js.15c7afe06aa7d42f9bf8.js
jupyterlab_mutableai_optin/labextension/static/lib_index_js.15c7afe06aa7d42f9bf8.js.map
jupyterlab_mutableai_optin/labextension/static/remoteEntry.06929fa84bd0acd51097.js
jupyterlab_mutableai_optin/labextension/static/remoteEntry.06929fa84bd0acd51097.js.map
jupyterlab_mutableai_optin/labextension/static/style.js
jupyterlab_mutableai_optin/labextension/static/style_index_js.1f38497bbe239d5099f6.js
jupyterlab_mutableai_optin/labextension/static/style_index_js.1f38497bbe239d5099f6.js.map
jupyterlab_mutableai_optin/labextension/static/vendors-node_modules_css-loader_dist_runtime_api_js-node_modules_css-loader_dist_runtime_cssW-72eba1.91ee287be3cdab384a77.js
jupyterlab_mutableai_optin/labextension/static/vendors-node_modules_css-loader_dist_runtime_api_js-node_modules_css-loader_dist_runtime_cssW-72eba1.91ee287be3cdab384a77.js.map
jupyterlab_mutableai_optin/labextension/static/vendors-node_modules_html-react-parser_index_mjs.d8bd9c132ead7f85337b.js
jupyterlab_mutableai_optin/labextension/static/vendors-node_modules_html-react-parser_index_mjs.d8bd9c132ead7f85337b.js.map
jupyterlab_mutableai_optin-0.1.0.data/data/share/jupyter/labextensions/jupyterlab_mutableai_optin/build_log.json
jupyterlab_mutableai_optin-0.1.0.data/data/share/jupyter/labextensions/jupyterlab_mutableai_optin/install.json
jupyterlab_mutableai_optin-0.1.0.data/data/share/jupyter/labextensions/jupyterlab_mutableai_optin/package.json
jupyterlab_mutableai_optin-0.1.0.data/data/share/jupyter/labextensions/jupyterlab_mutableai_optin/static/551302024f9f9dcad3fd02d7bbfcd628cf81d75a81202edb87758d23aaa619ab.png
jupyterlab_mutableai_optin-0.1.0.dist-info/LICENSE
jupyterlab_mutableai_optin-0.1.0.dist-info/METADATA
jupyterlab_mutableai_optin-0.1.0.dist-info/WHEEL
jupyterlab_mutableai_optin-0.1.0.dist-info/top_level.txt
jupyterlab_mutableai_optin-0.1.0.dist-info/RECORD
